.gitignore
.travis.yml
LICENSE
MANIFEST.in
README.md
requirements.txt
setup.py
version.py
MICA/__init__.py
MICA/mica.py
MICA/mica_ge.py
MICA/mica_mds.py
MICA/mica_pca.py
MICA/mica_umap.py
MICA.egg-info/PKG-INFO
MICA.egg-info/SOURCES.txt
MICA.egg-info/dependency_links.txt
MICA.egg-info/entry_points.txt
MICA.egg-info/requires.txt
MICA.egg-info/top_level.txt
MICA/analysis/__init__.py
MICA/analysis/evaluation/__init__.py
MICA/analysis/evaluation/clustering_performance/ID_conversion.R
MICA/analysis/evaluation/clustering_performance/__init__.py
MICA/analysis/evaluation/clustering_performance/eval.py
MICA/analysis/evaluation/clustering_performance/eval_golden.ipynb
MICA/analysis/evaluation/clustering_performance/eval_scnapy.py
MICA/analysis/evaluation/clustering_performance/scatter_plot_true_label.py
MICA/analysis/evaluation/clustering_performance/utils.py
MICA/analysis/evaluation/clustering_performance/Activity/PBMC_20k_CD4T.R
MICA/analysis/evaluation/clustering_performance/Activity/PBMC_20k_global.R
MICA/analysis/evaluation/clustering_performance/Activity/eval_PBMC_20k.py
MICA/analysis/evaluation/clustering_performance/Activity/marker_score_MICA_PBMC_14k.R
MICA/analysis/evaluation/clustering_performance/Activity/network_QC.R
MICA/analysis/evaluation/clustering_performance/GoldenStd/__init__.py
MICA/analysis/evaluation/clustering_performance/GoldenStd/debug_Buettner.py
MICA/analysis/evaluation/clustering_performance/GoldenStd/eval_Buettner.py
MICA/analysis/evaluation/clustering_performance/GoldenStd/eval_Goolam.py
MICA/analysis/evaluation/clustering_performance/GoldenStd/eval_Kolod.py
MICA/analysis/evaluation/clustering_performance/GoldenStd/eval_PBMC_20K.py
MICA/analysis/evaluation/clustering_performance/GoldenStd/eval_Pollen.py
MICA/analysis/evaluation/clustering_performance/GoldenStd/eval_Yan.py
MICA/analysis/evaluation/clustering_performance/LCA/LCA.vs.MICA.R
MICA/analysis/evaluation/clustering_performance/SC3/Rplots.pdf
MICA/analysis/evaluation/clustering_performance/SC3/cmd.sh
MICA/analysis/evaluation/clustering_performance/SC3/eval_Buettner.R
MICA/analysis/evaluation/clustering_performance/SC3/eval_Chung.R
